migu_test_pass_through/__init__.py
migu_test_pass_through/pass_through.py
migu_test_pass_through_xiaoming_debug-0.0.6.dist-info/LICENSE
migu_test_pass_through_xiaoming_debug-0.0.6.dist-info/METADATA
migu_test_pass_through_xiaoming_debug-0.0.6.dist-info/WHEEL
migu_test_pass_through_xiaoming_debug-0.0.6.dist-info/top_level.txt
migu_test_pass_through_xiaoming_debug-0.0.6.dist-info/RECORD
