Metadata-Version: 2.1
Name: migu-test-pass-through-xiaoming-debug
Version: 0.0.6
Summary: A small example package just pass through the input data
Home-page: https://github.com/pypa/sampleproject
Author: Test User
Author-email: author@example.com
License: UNKNOWN
Project-URL: Bug Tracker, https://github.com/pypa/sampleproject/issues
Platform: UNKNOWN
Classifier: Programming Language :: Python :: 3
Classifier: License :: OSI Approved :: MIT License
Classifier: Operating System :: OS Independent
Requires-Python: >=3.6
License-File: LICENSE
